Metadata-Version: 2.4
Name: coqui-tts-trainer
Version: 0.3.2
Summary: General purpose model trainer for PyTorch that is more flexible than it should be, by 🐸Coqui.
Project-URL: Homepage, https://github.com/idiap/coqui-ai-Trainer
Project-URL: Repository, https://github.com/idiap/coqui-ai-Trainer
Project-URL: Issues, https://github.com/idiap/coqui-ai-Trainer/issues
Author-email: Eren Gölge <egolge@coqui.ai>
Maintainer-email: Enno Hermann <enno.hermann@gmail.com>
License: Apache-2.0
License-File: LICENSE.txt
Classifier: Development Status :: 4 - Beta
Classifier: Environment :: Console
Classifier: Intended Audience :: Developers
Classifier: Intended Audience :: Science/Research
Classifier: License :: OSI Approved :: Apache Software License
Classifier: Natural Language :: English
Classifier: Operating System :: OS Independent
Classifier: Programming Language :: Python
Classifier: Programming Language :: Python :: 3
Classifier: Programming Language :: Python :: 3.10
Classifier: Programming Language :: Python :: 3.11
Classifier: Programming Language :: Python :: 3.12
Classifier: Programming Language :: Python :: 3.13
Classifier: Programming Language :: Python :: 3.14
Classifier: Topic :: Scientific/Engineering :: Artificial Intelligence
Classifier: Topic :: Software Development
Classifier: Topic :: Software Development :: Libraries :: Python Modules
Requires-Python: <3.15,>=3.10
Requires-Dist: coqpit-config<0.3.0,>=0.2.2
Requires-Dist: fsspec>=2023.6.0
Requires-Dist: numpy>=1.25.2; python_version < '3.12'
Requires-Dist: numpy>=1.26.0; python_version == '3.12'
Requires-Dist: numpy>=2.1.0; python_version == '3.13'
Requires-Dist: numpy>=2.3.2; python_version >= '3.13'
Requires-Dist: packaging>=21.0
Requires-Dist: psutil>=7
Requires-Dist: soundfile>=0.12.0
Requires-Dist: tensorboard>=2.17.1
Requires-Dist: torch>=2.2; python_version < '3.12'
Requires-Dist: torch>=2.3; python_version == '3.12'
Requires-Dist: torch>=2.6; python_version == '3.13'
Requires-Dist: torch>=2.9; python_version >= '3.14'
